globy_core/__init__.py
globy_core/common/helpers.py
globy_core/experimental/api/private.py
globy_core/experimental/api/public.py
globy_core/experimental/cms/sitebuilder.py
globy_core/experimental/cms/sitebuilder_test.py
globy_core/experimental/interaction/globy-interaction.py
globy_core/logging/logger.py
globy_core/ml/README.md
globy_core/ml/__init__.py
globy_core/ml/datamodel.py
globy_core/ml/inference-preprocess.py
globy_core/ml/inference.py
globy_core/security/auth.py
globy_core/store/database.py
globy_core/store/queue.py
globy_core/store/test_mongodb.py
globy_core-0.0.14.dist-info/METADATA
globy_core-0.0.14.dist-info/WHEEL
globy_core-0.0.14.dist-info/top_level.txt
globy_core-0.0.14.dist-info/RECORD
