Metadata-Version: 2.1
Name: globy_core
Version: 0.0.14
Summary: Globy Core
Author-email: Björn L <bjorn@globy.ai>
Project-URL: Homepage, https://github.com/globyai
Classifier: Programming Language :: Python :: 3
Classifier: License :: OSI Approved :: MIT License
Classifier: Operating System :: OS Independent
Requires-Python: >=3.9
Requires-Dist: colorlog
